brainunit/__init__.py
brainunit/_base.py
brainunit/_celsius.py
brainunit/_unit_common.py
brainunit/_unit_constants.py
brainunit/_unit_shortcuts.py
brainunit/constants.py
brainunit/autograd/__init__.py
brainunit/autograd/_hessian.py
brainunit/autograd/_jacobian.py
brainunit/autograd/_value_and_grad.py
brainunit/autograd/_vector_grad.py
brainunit/fft/__init__.py
brainunit/fft/_fft_change_unit.py
brainunit/fft/_fft_keep_unit.py
brainunit/lax/__init__.py
brainunit/lax/_lax_accept_unitless.py
brainunit/lax/_lax_array_creation.py
brainunit/lax/_lax_change_unit.py
brainunit/lax/_lax_keep_unit.py
brainunit/lax/_lax_linalg.py
brainunit/lax/_lax_remove_unit.py
brainunit/lax/_misc.py
brainunit/linalg/__init__.py
brainunit/linalg/_linalg_change_unit.py
brainunit/linalg/_linalg_keep_unit.py
brainunit/linalg/_linalg_remove_unit.py
brainunit/math/__init__.py
brainunit/math/_activation.py
brainunit/math/_alias.py
brainunit/math/_einops.py
brainunit/math/_fun_accept_unitless.py
brainunit/math/_fun_array_creation.py
brainunit/math/_fun_change_unit.py
brainunit/math/_fun_keep_unit.py
brainunit/math/_fun_remove_unit.py
brainunit/math/_misc.py
brainunit/math/fft.py
brainunit/math/linalg.py
brainunit/sparse/__init__.py
brainunit/sparse/_block_csr.py
brainunit/sparse/_block_ell.py
brainunit/sparse/_coo.py
brainunit/sparse/_csr.py
brainunit-0.1.4.dist-info/METADATA
brainunit-0.1.4.dist-info/WHEEL
brainunit-0.1.4.dist-info/top_level.txt
brainunit-0.1.4.dist-info/RECORD
